{
  "status": "PASS_NEEDS_MANUAL_UI_REVIEW",
  "command": "npm test -- basic-result-full-unlock",
  "requirementIds": [
    "REQ143-004",
    "REQ143-007",
    "REQ143-008",
    "REQ143-009"
  ],
  "ownerScenarioIds": [
    "O143-03",
    "O143-04"
  ],
  "uiReferences": [
    "docs/UI/小程序/v1.4.3-C07-完整初判-9.9解锁.png",
    "docs/UI/小程序/v1.4.3-C07-确认9.9支付半屏弹窗.png"
  ],
  "visualEvidence": {
    "status": "PASS_NEEDS_MANUAL_UI_REVIEW",
    "expectedVisualCommand": "npm run visual:scoremap -- basic-result full-unlock",
    "limitation": "Fresh C07 structural evidence can be generated locally; true WeChat runtime screenshot parity is not claimed in this child task."
  },
  "localOnly": {
    "status": "PASS",
    "localOnly": true,
    "adapterMode": "local-mock",
    "paymentAdapter": "local-wechat-pay-mock",
    "cloudAdapter": "local-tencent-cloud-mock",
    "databaseAdapter": "local-in-memory-db"
  },
  "forbiddenRemoteFindings": [],
  "secretFindings": []
}
