{
  "status": "PASS",
  "command": "npm --prefix server test -- report feedback export",
  "apiCalls": [
    {
      "method": "GET",
      "path": "/api/diagnosis-orders/{orderId}/basic-decision",
      "branch": "preview_only_denied",
      "responseStatus": 403,
      "response": {
        "status": "error",
        "code": "BASIC_ENTITLEMENT_REQUIRED"
      }
    },
    {
      "method": "GET",
      "path": "/api/diagnosis-orders/{orderId}/full-report",
      "branch": "owner_denial",
      "responseStatus": 403,
      "response": {
        "status": "error",
        "code": "ORDER_FORBIDDEN"
      }
    },
    {
      "method": "GET",
      "path": "/api/diagnosis-orders/{orderId}/full-report",
      "branch": "not_generated",
      "responseStatus": 409,
      "response": {
        "status": "error",
        "code": "FULL_REPORT_NOT_GENERATED"
      }
    },
    {
      "method": "POST",
      "path": "/api/feedbacks",
      "branch": "validation",
      "responseStatus": 400,
      "response": {
        "status": "error",
        "code": "VALIDATION_ERROR",
        "message": "decisionLevel must be basic or full."
      }
    },
    {
      "method": "GET",
      "path": "/api/report-exports/{exportId}",
      "branch": "not_found",
      "responseStatus": 404,
      "response": {
        "status": "error",
        "code": "NOT_FOUND",
        "message": "Report export not found."
      }
    }
  ],
  "dbReadback": {
    "previewOnlyOrder": {
      "id": "order-ad00ad5290b8",
      "ownerId": "local-user-scoremap-t03",
      "source": "T05-preview-only",
      "grade": "grade-5",
      "subject": "math",
      "examType": "unit-test",
      "materialType": "answer-sheet",
      "status": "preview_done",
      "accessLevel": "preview",
      "orderToken": "local-order-token-order-ad00ad5290b8",
      "createdAt": "2026-06-22T04:20:46.028Z",
      "updatedAt": "2026-06-22T04:20:46.198Z",
      "uploadedCount": 1,
      "previewTaskId": "task-e6ab58e7b0d1",
      "previewDecisionId": "decision-order-ad00ad5290b8-preview"
    },
    "protectedOrder": {
      "id": "order-14299934d83c",
      "ownerId": "local-user-scoremap-t03",
      "source": "T05-errors",
      "grade": "grade-5",
      "subject": "math",
      "examType": "unit-test",
      "materialType": "answer-sheet",
      "status": "full_paid",
      "accessLevel": "full",
      "orderToken": "local-order-token-order-14299934d83c",
      "createdAt": "2026-06-22T04:20:46.248Z",
      "updatedAt": "2026-06-22T04:20:46.475Z",
      "uploadedCount": 1,
      "previewTaskId": "task-9bddfe0592b1",
      "previewDecisionId": "decision-order-14299934d83c-preview"
    }
  }
}
